karellen/testing/mock/__init__.py
karellen_testing-0.0.1.dev20161012185112.dist-info/DESCRIPTION.rst
karellen_testing-0.0.1.dev20161012185112.dist-info/METADATA
karellen_testing-0.0.1.dev20161012185112.dist-info/RECORD
karellen_testing-0.0.1.dev20161012185112.dist-info/WHEEL
karellen_testing-0.0.1.dev20161012185112.dist-info/metadata.json
karellen_testing-0.0.1.dev20161012185112.dist-info/namespace_packages.txt
karellen_testing-0.0.1.dev20161012185112.dist-info/top_level.txt
karellen_testing-0.0.1.dev20161012185112.dist-info/zip-safe
