Metadata-Version: 2.0
Name: karellen-testing
Version: 0.0.1.dev20161012185112
Summary: Karellen Testing Frameworks and Utilities
Home-page: https://github.com/karellen/karellen-testing
Author: Karellen, Inc
Author-email: supervisor@karellen.co
License: Apache License, Version 2.0
Platform: UNKNOWN
Classifier: Development Status :: 5 - Production/Stable
Classifier: Environment :: Console
Classifier: Intended Audience :: Developers
Classifier: License :: OSI Approved :: Apache Software License
Classifier: Programming Language :: Python
Classifier: Programming Language :: Python :: 3.5
Classifier: Topic :: Software Development :: Libraries
Classifier: Topic :: Software Development :: Libraries :: Python Modules
Classifier: Topic :: Software Development :: Testing
